cli/__init__.py
cli/main.py
converter/__init__.py
converter/batch_processor.py
converter/data_validator.py
converter/error_handler.py
converter/multidimensional_handler.py
converter/performance_optimizer.py
converter/phz_converter.py
converter/resilience_config.py
converter/resilience_enhancements.py
converter/reverse_converter.py
converter/robust_converter.py
converter/schema_mapper.py
converter/sqlite_converter.py
pytopspeed/__init__.py
pytopspeed/test.py
pytopspeed/tps.py
pytopspeed/tpscrypt.py
pytopspeed/tpspage.py
pytopspeed/tpsrecord.py
pytopspeed/tpstable.py
pytopspeed/utils.py
pytopspeed_modernized-1.1.3.dist-info/licenses/LICENSE
pytopspeed_modernized-1.1.3.dist-info/METADATA
pytopspeed_modernized-1.1.3.dist-info/WHEEL
pytopspeed_modernized-1.1.3.dist-info/entry_points.txt
pytopspeed_modernized-1.1.3.dist-info/top_level.txt
pytopspeed_modernized-1.1.3.dist-info/RECORD
