Metadata-Version: 2.4
Name: pytopspeed-modernized
Version: 1.1.3
Summary: Modernized pytopspeed library for converting TopSpeed database files to SQLite
Home-page: https://github.com/gregeasley/pytopspeed_modernized
Author: Greg Easley
Author-email: Greg Easley <greg@easley.dev>
Maintainer-email: Greg Easley <greg@easley.dev>
License: MIT
Project-URL: Homepage, https://github.com/gregeasley/pytopspeed_modernized
Project-URL: Documentation, https://github.com/gregeasley/pytopspeed_modernized/blob/master/docs/README.md
Project-URL: Repository, https://github.com/gregeasley/pytopspeed_modernized
Project-URL: Bug Tracker, https://github.com/gregeasley/pytopspeed_modernized/issues
Keywords: topspeed,clarion,database,sqlite,conversion,migration,legacy
Classifier: Development Status :: 5 - Production/Stable
Classifier: Intended Audience :: Developers
Classifier: Intended Audience :: System Administrators
Classifier: License :: OSI Approved :: MIT License
Classifier: Operating System :: OS Independent
Classifier: Programming Language :: Python :: 3
Classifier: Programming Language :: Python :: 3.8
Classifier: Programming Language :: Python :: 3.9
Classifier: Programming Language :: Python :: 3.10
Classifier: Programming Language :: Python :: 3.11
Classifier: Programming Language :: Python :: 3.12
Classifier: Topic :: Database
Classifier: Topic :: Database :: Database Engines/Servers
Classifier: Topic :: Software Development :: Libraries :: Python Modules
Classifier: Topic :: System :: Archiving
Classifier: Topic :: Utilities
Requires-Python: >=3.8
License-File: LICENSE
Requires-Dist: construct>=2.10
Requires-Dist: click>=8.0.0
Requires-Dist: pandas>=1.5.0
Requires-Dist: psutil>=5.9.0
Provides-Extra: dev
Requires-Dist: pytest>=7.0.0; extra == "dev"
Requires-Dist: pytest-cov>=4.0.0; extra == "dev"
Requires-Dist: black>=22.0.0; extra == "dev"
Requires-Dist: flake8>=5.0.0; extra == "dev"
Requires-Dist: mypy>=1.0.0; extra == "dev"
Provides-Extra: docs
Requires-Dist: sphinx>=5.0.0; extra == "docs"
Requires-Dist: sphinx-rtd-theme>=1.0.0; extra == "docs"
Dynamic: author
Dynamic: home-page
Dynamic: license-file
Dynamic: requires-python
